odoo/addons/mgmtsystem_manual/README.rst
odoo/addons/mgmtsystem_manual/__init__.py
odoo/addons/mgmtsystem_manual/__manifest__.py
odoo/addons/mgmtsystem_manual/data/document_page.xml
odoo/addons/mgmtsystem_manual/i18n/de.po
odoo/addons/mgmtsystem_manual/i18n/es.po
odoo/addons/mgmtsystem_manual/i18n/fr.po
odoo/addons/mgmtsystem_manual/i18n/hr_HR.po
odoo/addons/mgmtsystem_manual/i18n/it.po
odoo/addons/mgmtsystem_manual/i18n/lv.po
odoo/addons/mgmtsystem_manual/i18n/mgmtsystem_manual.pot
odoo/addons/mgmtsystem_manual/i18n/mgmtsystem_manuals.pot
odoo/addons/mgmtsystem_manual/i18n/nb.po
odoo/addons/mgmtsystem_manual/i18n/nl_NL.po
odoo/addons/mgmtsystem_manual/i18n/nn.po
odoo/addons/mgmtsystem_manual/i18n/pt_BR.po
odoo/addons/mgmtsystem_manual/i18n/sl.po
odoo/addons/mgmtsystem_manual/i18n/sv.po
odoo/addons/mgmtsystem_manual/i18n/th.po
odoo/addons/mgmtsystem_manual/i18n/vi.po
odoo/addons/mgmtsystem_manual/models/__init__.py
odoo/addons/mgmtsystem_manual/models/mgmtsystem_system.py
odoo/addons/mgmtsystem_manual/static/description/icon.png
odoo/addons/mgmtsystem_manual/views/document_page.xml
odoo/addons/mgmtsystem_manual/views/mgmtsystem_system.xml
odoo11_addon_mgmtsystem_manual-11.0.1.1.0.99.dev5.dist-info/METADATA
odoo11_addon_mgmtsystem_manual-11.0.1.1.0.99.dev5.dist-info/WHEEL
odoo11_addon_mgmtsystem_manual-11.0.1.1.0.99.dev5.dist-info/top_level.txt
odoo11_addon_mgmtsystem_manual-11.0.1.1.0.99.dev5.dist-info/RECORD
